sandroid/__about.py
sandroid/__init__.py
sandroid/_version.py
sandroid/cli.py
sandroid/analysis/__init__.py
sandroid/analysis/changedfiles.py
sandroid/analysis/datagather.py
sandroid/analysis/deletedfiles.py
sandroid/analysis/fritap.py
sandroid/analysis/malwaremonitor.py
sandroid/analysis/network.py
sandroid/analysis/newfiles.py
sandroid/analysis/processes.py
sandroid/analysis/sockets.py
sandroid/analysis/static_analysis.py
sandroid/config/__init__.py
sandroid/config/android_env.py
sandroid/config/cli.py
sandroid/config/default.toml
sandroid/config/default.yaml
sandroid/config/loader.py
sandroid/config/schema.py
sandroid/config/theme.py
sandroid/core/AI_processing.py
sandroid/core/CustomLoggerFormatter.py
sandroid/core/__init__.py
sandroid/core/actionQ.py
sandroid/core/adb.py
sandroid/core/apk_downloader.py
sandroid/core/ccl_abx.py
sandroid/core/console.py
sandroid/core/emulator.py
sandroid/core/file_diff.py
sandroid/core/frida_manager.py
sandroid/core/fridump.py
sandroid/core/fsmon.py
sandroid/core/pdf_report.py
sandroid/core/progress.py
sandroid/core/timeline_generator.py
sandroid/core/toolbox.py
sandroid/core/events/__init__.py
sandroid/core/notifications/__init__.py
sandroid/core/notifications/handlers/__init__.py
sandroid/core/notifications/handlers/base.py
sandroid/core/notifications/handlers/gui.py
sandroid/core/notifications/handlers/web.py
sandroid/features/__init__.py
sandroid/features/functionality.py
sandroid/features/player.py
sandroid/features/recorder.py
sandroid/features/screenshot.py
sandroid/features/trigdroid.py
sandroid/tui/__init__.py
sandroid/tui/app.py
sandroid-1.7.6.dist-info/licenses/LICENSE
sandroid-1.7.6.dist-info/METADATA
sandroid-1.7.6.dist-info/WHEEL
sandroid-1.7.6.dist-info/entry_points.txt
sandroid-1.7.6.dist-info/top_level.txt
sandroid-1.7.6.dist-info/RECORD
