Metadata-Version: 2.4
Name: Sandroid
Version: 1.7.6
Summary: An Android sandbox for automated Forensic, Malware, and Security Analysis.
Author-email: Erik Nathrath <erik.nathrath@fkie.fraunhofer.de>, Daniel Baier <daniel.baier@fkie.fraunhofer.de>, Jan-Niclas Hilgert <jan-niclas.hilgert@fkie.fraunhofer.de>
Maintainer-email: Daniel Baier <daniel.baier@fkie.fraunhofer.de>, Erik Nathrath <erik.nathrath@fkie.fraunhofer.de>, Jan-Niclas Hilgert <jan-niclas.hilgert@fkie.fraunhofer.de>
License:                     GNU GENERAL PUBLIC LICENSE
Project-URL: Homepage, https://github.com/fkie-cad/Sandroid_core
Project-URL: Documentation, https://fkie-cad.github.io/Sandroid_core/
Project-URL: Repository, https://github.com/fkie-cad/Sandroid_core
Project-URL: Bug Tracker, https://github.com/fkie-cad/Sandroid_core/issues
Project-URL: Changelog, https://github.com/fkie-cad/Sandroid_core/blob/main/CHANGELOG.md
Project-URL: Authors, https://github.com/fkie-cad/Sandroid_core/blob/main/AUTHORS.md
Keywords: android,forensics,security,malware,analysis,frida,emulator
Classifier: Development Status :: 4 - Beta
Classifier: Environment :: Console
Classifier: Intended Audience :: Developers
Classifier: Intended Audience :: Information Technology
Classifier: License :: OSI Approved :: Apache Software License
Classifier: Operating System :: POSIX :: Linux
Classifier: Operating System :: MacOS :: MacOS X
Classifier: Programming Language :: Python :: 3
Classifier: Programming Language :: Python :: 3 :: Only
Classifier: Programming Language :: Python :: 3.10
Classifier: Programming Language :: Python :: 3.11
Classifier: Programming Language :: Python :: 3.12
Classifier: Topic :: Security
Classifier: Topic :: Software Development :: Testing
Classifier: Topic :: System :: Monitoring
Classifier: Natural Language :: English
Requires-Python: >=3.10
License-File: LICENSE
Requires-Dist: beautifulsoup4>=4.12.2
Requires-Dist: click>=8.1.7
Requires-Dist: colorama>=0.4.6
Requires-Dist: frida>=17.0.0
Requires-Dist: frida-tools>=14.0.0
Requires-Dist: lxml>=4.9.4
Requires-Dist: prompt-toolkit>=3.0.43
Requires-Dist: Pygments>=2.17.2
Requires-Dist: python-dateutil>=2.8.2
Requires-Dist: requests>=2.31.0
Requires-Dist: scapy>=2.5.0
Requires-Dist: six>=1.16.0
Requires-Dist: xmldiff>=2.7.0
Requires-Dist: tqdm>=4.64.0
Requires-Dist: reportlab>=4.0.0
Requires-Dist: geopy>=2.3.0
Requires-Dist: friTap>=1.3.1.4
Requires-Dist: colorlog>=6.7.0
Requires-Dist: objection<2.0.0,>=1.11.0
Requires-Dist: AndroidFridaManager>=1.9.0
Requires-Dist: trigdroid[full]>=2.0.1
Requires-Dist: dexray-intercept>=1.0.1.3
Requires-Dist: dexray-insight>=1.0.0.3
Requires-Dist: tomli>=2.0.1; python_version < "3.11"
Requires-Dist: tomli-w>=1.0.0
Requires-Dist: pyyaml>=6.0
Requires-Dist: pydantic>=2.0.0
Requires-Dist: platformdirs>=3.0.0
Requires-Dist: rich>=13.0.0
Requires-Dist: wcwidth>=0.2.13
Requires-Dist: thefuzz>=0.22.1
Requires-Dist: textual>=0.40.0
Provides-Extra: ai
Requires-Dist: google-generativeai>=0.3.0; extra == "ai"
Provides-Extra: dev
Requires-Dist: pytest>=7.0.0; extra == "dev"
Requires-Dist: pytest-cov>=4.0.0; extra == "dev"
Requires-Dist: pytest-mock>=3.10.0; extra == "dev"
Requires-Dist: ruff>=0.1.0; extra == "dev"
Requires-Dist: black>=23.0.0; extra == "dev"
Requires-Dist: isort>=5.12.0; extra == "dev"
Requires-Dist: flake8>=6.0.0; extra == "dev"
Requires-Dist: mypy>=1.0.0; extra == "dev"
Requires-Dist: bandit>=1.7.0; extra == "dev"
Requires-Dist: safety>=2.0.0; extra == "dev"
Requires-Dist: pre-commit>=3.0.0; extra == "dev"
Provides-Extra: docs
Requires-Dist: sphinx>=6.0.0; extra == "docs"
Requires-Dist: sphinx-rtd-theme>=1.2.0; extra == "docs"
Requires-Dist: myst-parser>=1.0.0; extra == "docs"
Dynamic: license-file
